Metadata-Version: 2.1
Name: mlp-mixer-keras
Version: 0.0.5
Summary: MLP-Mixer in Keras/Tensorflow
Home-page: https://github.com/Benjamin-Etheredge/mlp-mixer-keras
Author: Benjamin Etheredge
Author-email: 
License: MIT
Platform: UNKNOWN
Classifier: Development Status :: 4 - Beta
Classifier: Intended Audience :: Developers
Classifier: License :: OSI Approved :: MIT License
Classifier: Programming Language :: Python :: 3
Classifier: Topic :: Scientific/Engineering :: Artificial Intelligence
Classifier: Operating System :: OS Independent
